MtranHelperProject/__init__.py
MtranHelperProject/layers.py
MtranHelperProject/loggingin.py
MtranHelperProject/speedfilein.py
mtran_helper-0.0.1.dist-info/METADATA
mtran_helper-0.0.1.dist-info/WHEEL
mtran_helper-0.0.1.dist-info/top_level.txt
mtran_helper-0.0.1.dist-info/RECORD
